led_fsm.v
`timescale 1ns / 1ps

module led_fsm (
    input  wire       clk,
    input  wire       reset_n,
    output reg  [3:0] leds
);

    // state variable
    reg [1:0] state;

    // state values
    localparam S0 = 2'd0;
    localparam S1 =2'd1;
    localparam S2 = 2'd2;
    localparam S3 = 2'd3;

    // state transition
    always @(posedge clk or negedge reset_n) begin
        if (!reset_n) begin
            state <= S0;
            leds  <= 4'b0001;   //LED1 ON
        end else begin
            case (state)
                S0: begin
                    state <= S1;
                    leds  <= 4'b0010; // LED2 ON
                end
                S1: begin
                    state <= S2;
                    leds  <= 4'b0100; // LED3 ON
                end
                S2: begin
                    state <= S3;
                    leds  <= 4'b1000; //LED4 ON
                end
                S3: begin
                    state <= S0;
                    leds  <= 4'b0001; // LED1 ON
                end
            endcase
        end
    end

endmodule

led_fsm_tb.v
`timescale 1ns / 1ps


module led_fsm_tb;
    reg clk;
    reg reset_n;
    wire [3:0] leds;

    // DUT
    led_fsm dut (
        .clk(clk),
        .reset_n(reset_n),
        .leds(leds)
    );

    // clock 20 ns period
    initial begin
        clk = 0;
        forever #10 clk = ~clk;
    end

        initial begin
        $dumpfile("led_fsm.vcd");
        $dumpvars(0, led_fsm_tb);
    end

    initial begin
        reset_n = 0;
        #40;
        reset_n = 1;

        #200;
        $stop;
    end

endmodule

led_fsm.vcd
$date
	Sun Dec 28 23:44:59 2025
$end
$version
	Icarus Verilog
$end
$timescale
	1ps
$end
$scope module led_fsm_tb $end
$var wire 4 ! leds [3:0] $end
$var reg 1 " clk $end
$var reg 1 # reset_n $end
$scope module dut $end
$var wire 1 " clk $end
$var wire 1 # reset_n $end
$var parameter 2 $ S0 $end
$var parameter 2 % S1 $end
$var parameter 2 & S2 $end
$var parameter 2 ' S3 $end
$var reg 4 ( leds [3:0] $end
$var reg 2 ) state [1:0] $end
$upscope $end
$upscope $end
$enddefinitions $end
$comment Show the parameter values. $end
$dumpall
b11 '
b10 &
b1 %
b0 $
$end
#0
$dumpvars
b0 )
b1 (
0#
0"
b1 !
$end
#10000
1"
#20000
0"
#30000
1"
#40000
0"
1#
#50000
b10 !
b10 (
b1 )
1"
#60000
0"
#70000
b100 !
b100 (
b10 )
1"
#80000
0"
#90000
b1000 !
b1000 (
b11 )
1"
#100000
0"
#110000
b1 !
b1 (
b0 )
1"
#120000
0"
#130000
b10 !
b10 (
b1 )
1"
#140000
0"
#150000
b100 !
b100 (
b10 )
1"
#160000
0"
#170000
b1000 !
b1000 (
b11 )
1"
#180000
0"
#190000
b1 !
b1 (
b0 )
1"
#200000
0"
#210000
b10 !
b10 (
b1 )
1"
#220000
0"
#230000
b100 !
b100 (
b10 )
1"
